{
    "displayData": {
        "start_time": "2014-05-28",
        "end_time": "2014-11-30",
        "total_fee": "202207210.65",
        "card_ticket_ratio": "0%",
        "card_goods_ratio": "0.01%",
        "see_num": "4",
        "new_card_num": "48",
        "ticket_average": "90",
        "goods_consumption": "286240",
        "pay_way": {"ticket": "0%", "goods": "0.57%", "recharge": "99.43%"},
        "pay_type": {
            "cache": {"name": "现金", "value": "99.98%"},
            "bank": {"name": "POS刷卡", "value": "0.02%"},
            "internet": {"name": "网络支付", "value": "0.02%"},
            "coupon": {"name": "券支付", "value": "0%"},
            "card": {"name": "会员卡", "value": "0%"},
            "other": {"name": "其他", "value": "-0.02%"}
        }
    },
    "type": 1,
    "date": 1401206400
}